pyTMCL/__init__.py
pyTMCL/bus.py
pyTMCL/commands.py
pyTMCL/motor.py
pyTMCL/reply.py
pyTMCL/trigger_thread.py
pyTMCL-1.0.0.dist-info/LICENSE
pyTMCL-1.0.0.dist-info/METADATA
pyTMCL-1.0.0.dist-info/WHEEL
pyTMCL-1.0.0.dist-info/top_level.txt
pyTMCL-1.0.0.dist-info/RECORD
