Metadata-Version: 2.1
Name: pyTMCL
Version: 1.0.0
Summary: Talk to Trinamic Stepper Motors using TMCL over serial
Home-page: https://github.com/LukeSkywalker92/pyTMCL
Author: Lukas Scheffler
Author-email: luke@lukecodewalker.de
License: MIT
Keywords: tmcl,trinamic,rs485,stepper,motor,tmcm
Platform: UNKNOWN
Classifier: Programming Language :: Python :: 2
Classifier: Programming Language :: Python :: 3
Classifier: Development Status :: 5 - Production/Stable
Classifier: Intended Audience :: Developers
Classifier: Natural Language :: English
Classifier: License :: OSI Approved :: MIT License
Classifier: Operating System :: OS Independent
Requires-Dist: pyserial
